autotraders/__init__.py
autotraders/agent.py
autotraders/error.py
autotraders/paginated_list.py
autotraders/session.py
autotraders/space_traders_entity.py
autotraders/status.py
autotraders/time.py
autotraders/token.py
autotraders/util.py
autotraders/version.py
autotraders/faction/__init__.py
autotraders/faction/contract.py
autotraders/map/__init__.py
autotraders/map/system.py
autotraders/map/waypoint.py
autotraders/map/waypoint_types/__init__.py
autotraders/map/waypoint_types/construction.py
autotraders/map/waypoint_types/jumpgate.py
autotraders/map/waypoint_types/marketplace.py
autotraders/map/waypoint_types/shipyard.py
autotraders/shared_models/item.py
autotraders/shared_models/item_progress.py
autotraders/shared_models/map_symbol.py
autotraders/shared_models/ship_symbol.py
autotraders/shared_models/symbol.py
autotraders/shared_models/system_symbol.py
autotraders/shared_models/trait.py
autotraders/shared_models/transaction.py
autotraders/shared_models/waypoint_symbol.py
autotraders/ship/__init__.py
autotraders/ship/cargo.py
autotraders/ship/cooldown.py
autotraders/ship/fuel.py
autotraders/ship/nav.py
autotraders/ship/ship_components.py
autotraders/ship/states.py
autotraders/ship/survey.py
autotraders-2.3.5.dist-info/LICENSE
autotraders-2.3.5.dist-info/METADATA
autotraders-2.3.5.dist-info/WHEEL
autotraders-2.3.5.dist-info/top_level.txt
autotraders-2.3.5.dist-info/RECORD
