Metadata-Version: 2.1
Name: autotraders
Version: 2.3.5
Summary: A powerful spacetraders API
Author-email: Ashwin Naren <arihant2math@gmail.com>, Rafael Sillero <rafael.silnav@gmail.com>
Project-URL: Homepage, https://comsictraders.github.io/autotraders/
Project-URL: Repository, https://github.com/comsictraders/autotraders.git
Project-URL: Changelog, https://github.com/comsictraders/autotraders/blob/master/CHANGELOG.md
Project-URL: Documentation, https://comsictraders.github.io/autotraders/
Project-URL: Bug Tracker, https://github.com/comsictraders/autotraders/issues
Classifier: Programming Language :: Python :: 3
Classifier: Programming Language :: Python :: 3 :: Only
Classifier: Development Status :: 4 - Beta
Classifier: Topic :: Internet
Classifier: License :: OSI Approved :: MIT License
Classifier: Operating System :: OS Independent
Requires-Python: >=3.9
License-File: LICENSE
Requires-Dist: pyrate-limiter >3.0.0
Requires-Dist: pydantic >=2.0.0
Requires-Dist: httpx[http2] >=0.19.0
